demo.py
PygameUIKit/__init__.py
PygameUIKit/barchart.py
PygameUIKit/button.py
PygameUIKit/combobox.py
PygameUIKit/label.py
PygameUIKit/slider.py
PygameUIKit/super_object.py
PygameUIKit/text_input.py
PygameUIKit/utilis.py
PygameUIKit-0.1.1.dist-info/LICENSE.txt
PygameUIKit-0.1.1.dist-info/METADATA
PygameUIKit-0.1.1.dist-info/WHEEL
PygameUIKit-0.1.1.dist-info/top_level.txt
PygameUIKit-0.1.1.dist-info/RECORD
