Metadata-Version: 2.1
Name: PygameUIKit
Version: 0.1.1
Summary: A UIKit for Pygame
Author-email: Times0 <times.coding@gmail.com>
Classifier: Programming Language :: Python :: 3
Classifier: License :: OSI Approved :: MIT License
Classifier: Operating System :: OS Independent
Requires-Python: >=3.7
License-File: LICENSE.txt
